bitbucket/__init__.py
bitbucket/bitbucket.py
bitbucket/main.py
python_bitbucket_cli-1.4.0.dist-info/licenses/LICENSE
python_bitbucket_cli-1.4.0.dist-info/METADATA
python_bitbucket_cli-1.4.0.dist-info/WHEEL
python_bitbucket_cli-1.4.0.dist-info/entry_points.txt
python_bitbucket_cli-1.4.0.dist-info/top_level.txt
python_bitbucket_cli-1.4.0.dist-info/RECORD
