Metadata-Version: 2.4
Name: python-bitbucket-cli
Version: 1.4.0
Summary: A modern command-line interface for Bitbucket repositories
Home-page: https://github.com/mdminhazulhaque/python-bitbucket-cli
Author: Md Minhazul Haque
Author-email: mdminhazulhaque@gmail.com
Project-URL: Bug Reports, https://github.com/mdminhazulhaque/python-bitbucket-cli/issues
Project-URL: Source, https://github.com/mdminhazulhaque/python-bitbucket-cli
Keywords: bitbucket cli git devops pipeline api
Classifier: Development Status :: 5 - Production/Stable
Classifier: Intended Audience :: Developers
Classifier: Intended Audience :: System Administrators
Classifier: Topic :: Software Development :: Version Control
Classifier: Topic :: System :: Systems Administration
Classifier: License :: OSI Approved :: MIT License
Classifier: Operating System :: OS Independent
Classifier: Programming Language :: Python :: 3
Classifier: Programming Language :: Python :: 3.7
Classifier: Programming Language :: Python :: 3.8
Classifier: Programming Language :: Python :: 3.9
Classifier: Programming Language :: Python :: 3.10
Classifier: Programming Language :: Python :: 3.11
Classifier: Programming Language :: Python :: 3.12
Requires-Python: >=3.7
License-File: LICENSE
Requires-Dist: requests>=2.25.0
Requires-Dist: click>=8.0.0
Requires-Dist: tabulate>=0.8.0
Dynamic: author
Dynamic: author-email
Dynamic: classifier
Dynamic: description
Dynamic: description-content-type
Dynamic: home-page
Dynamic: keywords
Dynamic: license-file
Dynamic: project-url
Dynamic: requires-dist
Dynamic: requires-python
Dynamic: summary
